protmo/__init__.py
protmo/ast.py
protmo/create_proto_file.py
protmo/dart_ast.py
protmo/db.py
protmo/grpc_ast.py
protmo/name_to_protobuf.py
protmo/pm.py
protmo/provide.py
protmo/regen.py
protmo/settings_loader.py
protmo/utils.py
protmo/server/__init__.py
protmo/server/auth_interceptor.py
protmo/server/generic_servicer.py
protmo/server/open_id.py
protmo/server/server.py
protmo/server/user.py
test/__init__.py
test/test_settings.py
protmo-0.0.35.dist-info/METADATA
protmo-0.0.35.dist-info/WHEEL
protmo-0.0.35.dist-info/top_level.txt
protmo-0.0.35.dist-info/RECORD
