Metadata-Version: 2.1
Name: protmo
Version: 0.0.35
Summary: UNKNOWN
Home-page: UNKNOWN
Author: Thomas Deniffel
Author-email: tdeniffel@gmail.com
License: UNKNOWN
Platform: UNKNOWN
Classifier: Development Status :: 4 - Beta
Classifier: Intended Audience :: Developers
Classifier: Programming Language :: Python
Classifier: Programming Language :: Python :: 3.10
Requires-Python: >=3
Requires-Dist: grpcio-tools
Requires-Dist: pymongo
Requires-Dist: python-keycloak
